main.py
personal_library_managing_system-0.2.1.dist-info/METADATA
personal_library_managing_system-0.2.1.dist-info/WHEEL
personal_library_managing_system-0.2.1.dist-info/entry_points.txt
personal_library_managing_system-0.2.1.dist-info/top_level.txt
personal_library_managing_system-0.2.1.dist-info/RECORD
