Metadata-Version: 2.2
Name: personal-library-managing-system
Version: 0.2.1
Summary: A CLI-based personal library manager
Author-email: Syeda Darakhshan <darakhshanimranid@gmail.com>
Requires-Python: >=3.13
Requires-Dist: dotenv>=0.9.9
Requires-Dist: inquirer>=3.4.0
Requires-Dist: mysql-connector-python>=9.2.0
